today/cli.py
today/parser.py
today/scripts/start.py
today/scripts/today.py
today/task.py
todo_today_cli-0.0.8.dist-info/METADATA
todo_today_cli-0.0.8.dist-info/WHEEL
todo_today_cli-0.0.8.dist-info/entry_points.txt
todo_today_cli-0.0.8.dist-info/RECORD
