Metadata-Version: 2.1
Name: todo-today-cli
Version: 0.0.8
Summary: A file-centric task management app
Home-page: https://github.com/vighneshiyer/today
Author: Vighnesh Iyer
Author-email: vighnesh.iyer@gmail.com
Maintainer: Vighnesh Iyer
Maintainer-email: vighnesh.iyer@gmail.com
Requires-Python: >=3.9,<4.0
Classifier: Programming Language :: Python :: 3
Classifier: Programming Language :: Python :: 3.9
Classifier: Programming Language :: Python :: 3.10
Classifier: Programming Language :: Python :: 3.11
Classifier: Programming Language :: Python :: 3.12
Requires-Dist: more-itertools (>=10.2,<11.0)
Requires-Dist: pydantic (>=2.6.4,<3.0.0)
Requires-Dist: rich (>=13.7,<14.0)
Project-URL: Repository, https://github.com/vighneshiyer/today
